promptml/__about__.py
promptml/__init__.py
promptml/grammar.lark
promptml/parser.py
promptml/serializer.py
promptml-0.6.1.dist-info/METADATA
promptml-0.6.1.dist-info/WHEEL
promptml-0.6.1.dist-info/licenses/LICENSE
promptml-0.6.1.dist-info/RECORD
