Metadata-Version: 2.3
Name: promptml
Version: 0.6.1
Summary: A simple, yet elegant markup language for defining AI Prompts as Code (APaC). Built to be used by AI agents to automatically prompt for other AI systems
Project-URL: Documentation, https://github.com/narenaryan/promptml/blob/main/README.md
Project-URL: Issues, https://github.com/narenaryan/promptml/issues
Project-URL: Source, https://github.com/narenaryan/promptml/
Author-email: "Vidura Labs Inc." <contact@vidura.ai>, Naren Yellavula <naren.yellavula@gmail.com>
License-Expression: MIT
License-File: LICENSE
Keywords: artificial-intelligence,dsl,generative-ai,language,prompt-engineering
Classifier: Development Status :: 4 - Beta
Classifier: Programming Language :: Python
Classifier: Programming Language :: Python :: 3.8
Classifier: Programming Language :: Python :: 3.9
Classifier: Programming Language :: Python :: 3.10
Classifier: Programming Language :: Python :: 3.11
Classifier: Programming Language :: Python :: 3.12
Classifier: Programming Language :: Python :: Implementation :: CPython
Classifier: Programming Language :: Python :: Implementation :: PyPy
Requires-Python: >=3.8
Requires-Dist: lark==1.1.9
Requires-Dist: pyyaml==6.0.1
